pycredits/__init__.py
pycredits/column_histogram.py
pycredits/data_preprocessing.py
pycredits/label_mapper.py
pycredits/param_grid.py
pycredits-0.0.3.dist-info/LICENSE
pycredits-0.0.3.dist-info/METADATA
pycredits-0.0.3.dist-info/WHEEL
pycredits-0.0.3.dist-info/RECORD
