Metadata-Version: 2.1
Name: pycredits
Version: 0.0.3
Summary: A package for running data analyses around credit risk.
License: MIT
Author: Jade Bouchard
Requires-Python: >=3.9
Classifier: License :: OSI Approved :: MIT License
Classifier: Programming Language :: Python :: 3
Classifier: Programming Language :: Python :: 3.9
Classifier: Programming Language :: Python :: 3.10
Classifier: Programming Language :: Python :: 3.11
Classifier: Programming Language :: Python :: 3.12
Requires-Dist: matplotlib (>=3.8.4)
Requires-Dist: numpy (>=1.26.4)
Requires-Dist: pandas (>=2.2.1)
Requires-Dist: scikit-learn (>=1.4.1.post1)
Requires-Dist: seaborn (>=0.13.2)
